ActixWebZhongwenWendangFix1/README.md
ActixWebZhongwenWendangFix1/__init__.py
ActixWebZhongwenWendangFix1/__main__.py
ActixWebZhongwenWendangFix1/file.epub
ActixWebZhongwenWendangFix1/index.html
ActixWebZhongwenWendangFix1/css/__init__.py
ActixWebZhongwenWendangFix1/css/annotations.css
ActixWebZhongwenWendangFix1/css/main.css
ActixWebZhongwenWendangFix1/css/normalize.css
ActixWebZhongwenWendangFix1/css/popup.css
ActixWebZhongwenWendangFix1/font/__init__.py
ActixWebZhongwenWendangFix1/font/fontello.eot
ActixWebZhongwenWendangFix1/font/fontello.svg
ActixWebZhongwenWendangFix1/font/fontello.ttf
ActixWebZhongwenWendangFix1/font/fontello.woff
ActixWebZhongwenWendangFix1/img/__init__.py
ActixWebZhongwenWendangFix1/img/annotator-glyph-sprite.png
ActixWebZhongwenWendangFix1/img/annotator-icon-sprite.png
ActixWebZhongwenWendangFix1/img/apple-touch-icon.png
ActixWebZhongwenWendangFix1/img/cancelfullscreen.png
ActixWebZhongwenWendangFix1/img/close.png
ActixWebZhongwenWendangFix1/img/fullscreen.png
ActixWebZhongwenWendangFix1/img/loader.gif
ActixWebZhongwenWendangFix1/img/menu-icon.png
ActixWebZhongwenWendangFix1/img/save.png
ActixWebZhongwenWendangFix1/img/saved.png
ActixWebZhongwenWendangFix1/img/settings-s.png
ActixWebZhongwenWendangFix1/img/settings.png
ActixWebZhongwenWendangFix1/img/star.png
ActixWebZhongwenWendangFix1/js/__init__.py
ActixWebZhongwenWendangFix1/js/epub.js
ActixWebZhongwenWendangFix1/js/epub.min.js
ActixWebZhongwenWendangFix1/js/epub.min.map
ActixWebZhongwenWendangFix1/js/hooks.min.js
ActixWebZhongwenWendangFix1/js/hooks.min.map
ActixWebZhongwenWendangFix1/js/reader.js
ActixWebZhongwenWendangFix1/js/reader.js.map
ActixWebZhongwenWendangFix1/js/reader.min.js
ActixWebZhongwenWendangFix1/js/reader.min.map
ActixWebZhongwenWendangFix1/js/hooks/__init__.py
ActixWebZhongwenWendangFix1/js/hooks/extensions/__init__.py
ActixWebZhongwenWendangFix1/js/hooks/extensions/highlight.js
ActixWebZhongwenWendangFix1/js/libs/__init__.py
actix_web_zhongwen_wendang_fix1-2025.3.25.1.dist-info/METADATA
actix_web_zhongwen_wendang_fix1-2025.3.25.1.dist-info/WHEEL
actix_web_zhongwen_wendang_fix1-2025.3.25.1.dist-info/entry_points.txt
actix_web_zhongwen_wendang_fix1-2025.3.25.1.dist-info/top_level.txt
actix_web_zhongwen_wendang_fix1-2025.3.25.1.dist-info/RECORD
